{
  "display": {
    "icon": {
      "item": "minecraft:jukebox"
    },
    "title": {
      "translate": "technology.music.name"
    },
    "description": {
      "translate": "technology.music.desc"
    },
    "x": 2,
    "y": 2
  },
  "parent": "ftgumod:power/power",
  "idea": {
    "amount": 2,
    "ingredients": [
      {
        "type": "forge:ore_dict",
        "ore": "dustRedstone"
      },
      {
        "type": "forge:ore_dict",
        "ore": "gemDiamond"
      },
      {
        "type": "forge:ore_dict",
        "ore": "plankWood"
      }
    ]
  },
  "research": {
    "type": "ftgumod:match",
    "pattern": [
      " DI",
      " R ",
      "WWW"
    ],
    "key": {
      "I": {
        "item": [
          {
            "type": "forge:ore_dict",
            "ore": "stickWood"
          },
          {
            "type": "forge:ore_dict",
            "ore": "ingotIron"
          }
        ],
        "hint": {
          "translate": "technology.hint.arm"
        }
      },
      "D": {
        "item": [
          {
            "type": "forge:ore_dict",
            "ore": "nuggetIron"
          },
          {
            "type": "forge:ore_dict",
            "ore": "nuggetGold"
          },
          {
            "type": "forge:ore_dict",
            "ore": "gemDiamond"
          }
        ],
        "hint": {
          "translate": "technology.hint.stylus"
        }
      },
      "R": {
        "item": {
          "type": "forge:ore_dict",
          "ore": "record"
        },
        "hint": {
          "translate": "technology.hint.record"
        }
      },
      "W": {
        "item": [
          {
            "type": "forge:ore_dict",
            "ore": "plankWood"
          },
          {
            "type": "forge:ore_dict",
            "ore": "slabWood"
          }
        ],
        "hint": {
          "translate": "technology.hint.table"
        }
      }
    }
  },
  "unlock": [
    "minecraft:noteblock",
    "minecraft:jukebox"
  ]
}
